arcadezero/__init__.py
arcadezero/examples/__init__.py
arcadezero/examples/coin_paradize.py
arcadezero/sounds.py
arcadezero-0.0.2.dist-info/LICENSE
arcadezero-0.0.2.dist-info/WHEEL
arcadezero-0.0.2.dist-info/METADATA
arcadezero-0.0.2.dist-info/RECORD
