Metadata-Version: 2.1
Name: arcadezero
Version: 0.0.2
Summary: A beginner friendly layer on top of Arcade to create your very first game
Home-page: https://github.com/eruvanos/arcadezero
License: MIT
Keywords: arcade,beginner
Author: Maic Siemering
Author-email: maic@siemering.tech
Requires-Python: >=3.8,<4.0
Classifier: Development Status :: 3 - Alpha
Classifier: Intended Audience :: Developers
Classifier: License :: OSI Approved :: MIT License
Classifier: Operating System :: OS Independent
Classifier: Programming Language :: Python
Classifier: Programming Language :: Python :: 3
Classifier: Programming Language :: Python :: 3.6
Classifier: Programming Language :: Python :: 3.7
Classifier: Programming Language :: Python :: 3.8
Classifier: Programming Language :: Python :: 3.9
Classifier: Topic :: Games/Entertainment :: Arcade
Classifier: Topic :: Software Development :: Libraries :: Python Modules
Requires-Dist: arcade (>=2.5.7,<3.0.0)
Project-URL: Repository, https://github.com/eruvanos/arcadezero
